python_gh_template/__init__.py
python_gh_template/main.py
python_gh_template-1.0.0.dist-info/LICENSE
python_gh_template-1.0.0.dist-info/METADATA
python_gh_template-1.0.0.dist-info/WHEEL
python_gh_template-1.0.0.dist-info/top_level.txt
python_gh_template-1.0.0.dist-info/RECORD
