Metadata-Version: 2.1
Name: python-gh-template
Version: 1.0.0
Summary: Repo Template for creating a Python library in GitHub
Home-page: https://github.com/Cyb3r-Jak3/python_template_repo
Author: Cyber_Jake
Author-email: jake@jwhite.network
License: MPL 2.0
Download-URL: https://github.com/Cyb3r-Jak3/python_template_repo/releases/latest
Project-URL: Changelog, https://github.com/Cyb3r-Jak3/python_template_repo/blob/master/CHANGELOG.md
Project-URL: Issues, https://github.com/Cyb3r-Jak3/python_template_repo/issues
Keywords: template,github
Platform: UNKNOWN
Classifier: Development Status :: 5 - Production/Stable
Classifier: Intended Audience :: Developers
Classifier: License :: OSI Approved :: Mozilla Public License 2.0 (MPL 2.0)
Classifier: Natural Language :: English
Classifier: Programming Language :: Python :: 3 :: Only
Classifier: Programming Language :: Python :: 3
Classifier: Programming Language :: Python :: 3.6
Classifier: Programming Language :: Python :: 3.7
Classifier: Programming Language :: Python :: 3.8
Classifier: Programming Language :: Python :: 3.9
Classifier: Programming Language :: Python :: Implementation :: CPython
